pthree/__init__.py
pthree/_core.py
pthree-1.0.1.dist-info/licenses/LICENSE.txt
pthree-1.0.1.dist-info/METADATA
pthree-1.0.1.dist-info/WHEEL
pthree-1.0.1.dist-info/top_level.txt
pthree-1.0.1.dist-info/RECORD
