Metadata-Version: 2.4
Name: pthree
Version: 1.0.1
Summary: Python project parser used to generate member trees for sphinx autosummary documentation.
Author: Ryder Davidson
Author-email: "Predictive Science Inc." <webmaster@predsci.com>
License-Expression: Apache-2.0
Project-URL: homepage, https://predsci.com/
Project-URL: repository, https://github.com/predsci/pthree
Keywords: documentation,parser,psi
Classifier: Development Status :: 4 - Beta
Classifier: Intended Audience :: Science/Research
Classifier: Natural Language :: English
Classifier: Programming Language :: Python :: 3
Classifier: Operating System :: OS Independent
Requires-Python: >=3.10
License-File: LICENSE.txt
Dynamic: license-file
